jyro/__init__.py
jyro/myro/__init__.py
jyro/myro/chat.py
jyro/myro/chuck.py
jyro/myro/conx.py
jyro/myro/graphics.py
jyro/myro/intelhex.py
jyro/myro/media.py
jyro/myro/piano.py
jyro/myro/simulator.py
jyro/myro/speech.py
jyro/myro/system.py
jyro/myro/widgets.py
jyro/simulator/__init__.py
jyro/simulator/canvas.py
jyro/simulator/color.py
jyro/simulator/device.py
jyro/simulator/robot.py
jyro/simulator/simulator.py
jyro-0.3.2.dist-info/DESCRIPTION.rst
jyro-0.3.2.dist-info/METADATA
jyro-0.3.2.dist-info/RECORD
jyro-0.3.2.dist-info/WHEEL
jyro-0.3.2.dist-info/metadata.json
jyro-0.3.2.dist-info/top_level.txt
