Metadata-Version: 2.0
Name: jyro
Version: 0.3.2
Summary: Python tools for robots
Home-page: https://github.com/Calysto/jyro
Author: Douglas Blank
Author-email: doug.blank@gmail.com
License: UNKNOWN
Platform: UNKNOWN
Classifier: Framework :: IPython
Classifier: License :: OSI Approved :: BSD License
Classifier: Programming Language :: Python :: 3
Requires-Dist: calysto
